grumpy_checks/__init__.py
grumpy_checks/application.py
grumpy_checks/checks.py
grumpy_checks/cli/__init__.py
grumpy_checks/cli/about.py
grumpy_checks/cli/cat.py
grumpy_checks/cli/grumpy_report/lint.txt
grumpy_checks/commands.py
grumpy_checks/docs.py
grumpy_checks/everything.py
grumpy_checks/lint.py
grumpy_checks/news.py
grumpy_checks/tests.py
grumpy_checks/utils.py
grumpy_checks-0.1.7.dist-info/entry_points.txt
grumpy_checks-0.1.7.dist-info/WHEEL
grumpy_checks-0.1.7.dist-info/METADATA
grumpy_checks-0.1.7.dist-info/RECORD
